Topsis_Suddhasattwa_102003687/__init__.py
Topsis_Suddhasattwa_102003687/main.py
Topsis_SuddhasattwaKhan_102003687-0.0.1.dist-info/LICENSE
Topsis_SuddhasattwaKhan_102003687-0.0.1.dist-info/METADATA
Topsis_SuddhasattwaKhan_102003687-0.0.1.dist-info/WHEEL
Topsis_SuddhasattwaKhan_102003687-0.0.1.dist-info/top_level.txt
Topsis_SuddhasattwaKhan_102003687-0.0.1.dist-info/RECORD
