Metadata-Version: 2.1
Name: Topsis-SuddhasattwaKhan-102003687
Version: 0.0.1
Summary: A small example package
Author: Suddhasattwa Khan
Author-email: khansuddhasattwa@gmail.com
Classifier: Programming Language :: Python :: 3
Classifier: License :: OSI Approved :: MIT License
Classifier: Operating System :: OS Independent
Requires-Python: >=3.6
License-File: LICENSE
